netrix/__init__.py
netrix/netrix.py
netrix-0.1.0.dist-info/LICENSE
netrix-0.1.0.dist-info/METADATA
netrix-0.1.0.dist-info/WHEEL
netrix-0.1.0.dist-info/top_level.txt
netrix-0.1.0.dist-info/RECORD
